doggo/__init__.py
doggo/cli.py
doggo/config.py
doggo/database.py
doggo/indexer.py
doggo/openai_client.py
doggo/organizer.py
doggo/searcher.py
doggo/utils.py
doggo-0.3.0.dist-info/METADATA
doggo-0.3.0.dist-info/WHEEL
doggo-0.3.0.dist-info/entry_points.txt
doggo-0.3.0.dist-info/licenses/LICENSE
doggo-0.3.0.dist-info/RECORD
