Metadata-Version: 2.4
Name: doggo
Version: 0.3.0
Summary: Your loyal digital companion who finds files the way you think about them
Project-URL: Homepage, https://github.com/0nsh/doggo
Project-URL: Repository, https://github.com/0nsh/doggo
Project-URL: Issues, https://github.com/0nsh/doggo
Author: n0lan
License: MIT
License-File: LICENSE
Keywords: ai,cli,files,images,search,semantic
Classifier: Development Status :: 3 - Alpha
Classifier: Intended Audience :: Developers
Classifier: License :: OSI Approved :: MIT License
Classifier: Programming Language :: Python :: 3
Classifier: Programming Language :: Python :: 3.8
Classifier: Programming Language :: Python :: 3.9
Classifier: Programming Language :: Python :: 3.10
Classifier: Programming Language :: Python :: 3.11
Classifier: Programming Language :: Python :: 3.12
Classifier: Topic :: Desktop Environment :: File Managers
Classifier: Topic :: Utilities
Requires-Python: >=3.11
Requires-Dist: chromadb>=0.4.0
Requires-Dist: click>=8.1.7
Requires-Dist: openai>=1.0.0
Requires-Dist: pillow>=10.0.0
Requires-Dist: rich>=13.0.0
Provides-Extra: dev
Requires-Dist: black>=23.0.0; extra == 'dev'
Requires-Dist: coverage>=7.6.1; extra == 'dev'
Requires-Dist: flake8>=6.0.0; extra == 'dev'
Requires-Dist: pre-commit>=3.0.0; extra == 'dev'
Requires-Dist: pytest>=8.3.3; extra == 'dev'
